progressist/__init__.py
progressist-0.1.0.dist-info/METADATA
progressist-0.1.0.dist-info/WHEEL
progressist-0.1.0.dist-info/top_level.txt
progressist-0.1.0.dist-info/RECORD
