Metadata-Version: 2.1
Name: progressist
Version: 0.1.0
Summary: Minimalist and pythonic progress bar
Home-page: https://github.com/pyrates/progressist
Author: Yohan Boniface
Author-email: hi@yohanboniface.me
License: WTFPL
Keywords: progress bar
Platform: UNKNOWN
Classifier: Development Status :: 4 - Beta
Classifier: Intended Audience :: Developers
Classifier: Programming Language :: Python :: 3.4
Classifier: Programming Language :: Python :: 3.5
Classifier: Programming Language :: Python :: 3.6
Classifier: Programming Language :: Python :: 3.7
Provides-Extra: test
